grecy/__init__.py
grecy/__main__.py
grecy/utilities/__init__.py
grecy/utilities/connections.py
grecy-1.0.dist-info/LICENSE.txt
grecy-1.0.dist-info/METADATA
grecy-1.0.dist-info/WHEEL
grecy-1.0.dist-info/top_level.txt
grecy-1.0.dist-info/RECORD
