Metadata-Version: 2.1
Name: grecy
Version: 1.0
Summary: grecy installs six ancient Greek spaCy models that were trained using the Universal Dependency Proiel and Perseus treebanks.
Author-email: Jacobo Myerston <jmyerston@ucsd.edu>
License: MIT License
Project-URL: Homepage, https://github.com/jmyerston/greCy
Project-URL: Bug Tracker, https://github.com/jmyerston/greCy/issues
Classifier: Programming Language :: Python :: 3
Classifier: License :: OSI Approved :: MIT License
Classifier: Operating System :: OS Independent
Requires-Python: >=3.10
License-File: LICENSE.txt
Requires-Dist: spacy (<4.0.0,>=3.5)
